lazyimports/__init__.py
lazyimports/_context.py
lazyimports/_import_machinery.py
lazyimports/_modules.py
lazyimports/_proxy.py
lazyimports/py.typed
hatch_autorun_pylazyimports.pth
pylazyimports-0.5.2.dist-info/METADATA
pylazyimports-0.5.2.dist-info/WHEEL
pylazyimports-0.5.2.dist-info/licenses/LICENSE
pylazyimports-0.5.2.dist-info/RECORD
