Metadata-Version: 2.4
Name: pylazyimports
Version: 0.5.2
Summary: A module to enable lazy imports using native python syntax
Project-URL: Repository, https://github.com/hmiladhia/lazyimports
Project-URL: Issues, https://github.com/hmiladhia/lazyimports/issues
Author: Dhia Hmila
License: MIT License
License-File: LICENSE
Classifier: Intended Audience :: Developers
Classifier: License :: OSI Approved :: MIT License
Classifier: Programming Language :: Python :: 3
Classifier: Programming Language :: Python :: 3.10
Classifier: Programming Language :: Python :: 3.11
Classifier: Programming Language :: Python :: 3.12
Classifier: Programming Language :: Python :: 3.13
Classifier: Programming Language :: Python :: 3.14
Classifier: Typing :: Typed
Requires-Python: >=3.10
Requires-Dist: typing-extensions>=4.15.0; python_full_version < '3.11'
